Metadata-Version: 2.1
Name: mrr2c
Version: 3.0.0
Summary: Convert Metek MRR-2 micro rain radar data files to NetCDF
Home-page: https://github.com/peterkuma/mrr2c
Author: Peter Kuma
Author-email: peter@peterkuma.net
Keywords: metek,radar,mrr-2,netcdf
Classifier: Development Status :: 5 - Production/Stable
Classifier: Environment :: Console
Classifier: Intended Audience :: Science/Research
Classifier: License :: OSI Approved :: MIT License
Classifier: Operating System :: OS Independent
Classifier: Programming Language :: Python :: 3
Classifier: Topic :: Scientific/Engineering :: Atmospheric Science
License-File: LICENSE.md
